viur/scriptor/__init__.py
viur/scriptor/_utils.py
viur/scriptor/directory_handler.py
viur/scriptor/export_import.py
viur/scriptor/file.py
viur/scriptor/http_errors.py
viur/scriptor/logger.py
viur/scriptor/module.py
viur/scriptor/module_parts.py
viur/scriptor/progressbar.py
viur/scriptor/requests.py
viur/scriptor/utils.py
viur/scriptor/dialog/__init__.py
viur/scriptor/dialog/_validators.py
viur/scriptor/dialog/alert.py
viur/scriptor/dialog/confirm.py
viur/scriptor/dialog/date.py
viur/scriptor/dialog/diff.py
viur/scriptor/dialog/multiple.py
viur/scriptor/dialog/number.py
viur/scriptor/dialog/open_file.py
viur/scriptor/dialog/print.py
viur/scriptor/dialog/raw_html.py
viur/scriptor/dialog/save_file.py
viur/scriptor/dialog/select.py
viur/scriptor/dialog/table.py
viur/scriptor/dialog/text.py
viur_scriptor_api-1.12.0.dist-info/METADATA
viur_scriptor_api-1.12.0.dist-info/WHEEL
viur_scriptor_api-1.12.0.dist-info/licenses/LICENSE
viur_scriptor_api-1.12.0.dist-info/RECORD
