Metadata-Version: 2.4
Name: viur-scriptor-api
Version: 1.12.0
Summary: This is the internal Scriptor library that the viur-scriptor utilizes. The API includes components for networking as well as parts related to the Scriptor's files.
Project-URL: Documentation, https://viur-scriptor-api.readthedocs.io
Project-URL: Repository, https://github.com/viur-framework/viur-scriptor-api
Project-URL: Bug Tracker, https://github.com/viur-framework/viur-scriptor-api/issues
Author-email: Mausbrand Informationssysteme GmbH <devs@viur.dev>
License-Expression: MIT
License-File: LICENSE
Classifier: Development Status :: 5 - Production/Stable
Classifier: License :: OSI Approved :: MIT License
Classifier: Operating System :: OS Independent
Classifier: Programming Language :: Python :: 3
Classifier: Topic :: Software Development :: Interpreters
Requires-Python: >=3.10
Requires-Dist: chardet==5.2.0
Requires-Dist: openpyxl==3.1.5
Requires-Dist: prompt-toolkit==3.0.47
Requires-Dist: python-magic==0.4.27
Requires-Dist: requests==2.31.0
Requires-Dist: simple-term-menu==1.6.4
